{
    "searchParameters": {
        "q": "Joel Embiid NBA",
        "gl": "us",
        "hl": "en",
        "num": 10,
        "autocorrect": true,
        "page": 1,
        "type": "images",
        "engine": "google"
    },
    "images": [
        {
            "title": "Joel Embiid | Philadelphia 76ers | NBA.com",
            "imageUrl": "https://cdn.nba.com/headshots/nba/latest/1040x760/203954.png",
            "imageWidth": 1040,
            "imageHeight": 760,
            "thumbnailUrl": "https://encrypted-tbn0.gstatic.com/images?q=tbn:ANd9GcQHYxHXHxAFllm2sNlslom-ZF2uzB7jVBu__TKDQck9SVLLrlzv&amp;s",
            "thumbnailWidth": 263,
            "thumbnailHeight": 192,
            "source": "NBA.com",
            "domain": "www.nba.com",
            "link": "https://www.nba.com/player/203954/joel-embiid",
            "googleUrl": "https://www.google.com/imgres?imgurl=https%3A%2F%2Fcdn.nba.com%2Fheadshots%2Fnba%2Flatest%2F1040x760%2F203954.png&tbnid=nISH4i_ExH7x3M&imgrefurl=https%3A%2F%2Fwww.nba.com%2Fplayer%2F203954%2Fjoel-embiid&docid=7G3lib9frDkbgM&w=1040&h=760&ved=0ahUKEwiToJ3Wm_-CAxX6nokEHebSBh4QvFcIASgA",
            "position": 1
        },
        {
            "title": "Joel Embiid - Wikipedia",
            "imageUrl": "https://upload.wikimedia.org/wikipedia/commons/1/13/Joel_Embiid_2019.jpg",
            "imageWidth": 2428,
            "imageHeight": 3589,
            "thumbnailUrl": "https://encrypted-tbn0.gstatic.com/images?q=tbn:ANd9GcSrm07SDeKilcoo9flk8hvXzpiPfSLDj6htM8sfEFoq6Lo7PFE&amp;s",
            "thumbnailWidth": 185,
            "thumbnailHeight": 273,
            "source": "Wikipedia",
            "domain": "en.wikipedia.org",
            "link": "https://en.wikipedia.org/wiki/Joel_Embiid",
            "googleUrl": "https://www.google.com/imgres?imgurl=https%3A%2F%2Fupload.wikimedia.org%2Fwikipedia%2Fcommons%2F1%2F13%2FJoel_Embiid_2019.jpg&tbnid=Uq8XKE31v-m2mM&imgrefurl=https%3A%2F%2Fen.wikipedia.org%2Fwiki%2FJoel_Embiid&docid=ib_k4B1zlLXlmM&w=2428&h=3589&ved=0ahUKEwiToJ3Wm_-CAxX6nokEHebSBh4QvFcIAigB",
            "position": 2
        },
        {
            "title": "Sixers' Joel Embiid Worked With OKC Thunder's Chet Holmgren ...",
            "imageUrl": "https://www.si.com/.image/ar_1:1%2Cc_fill%2Ccs_srgb%2Cfl_progressive%2Cq_auto:good%2Cw_1200/MTkyODU5Mjg1OTcyMDY4MDQ4/usatsi_19146062_168388689_lowres.jpg",
            "imageWidth": 1200,
            "imageHeight": 1200,
            "thumbnailUrl": "https://encrypted-tbn0.gstatic.com/images?q=tbn:ANd9GcRz4hb5N-wPlLp-EBz0gTwZK9tqh-fQ7yar8BMQ9s0knKZ_avL_&amp;s",
            "thumbnailWidth": 225,
            "thumbnailHeight": 225,
            "source": "Sports Illustrated",
            "domain": "www.si.com",
            "link": "https://www.si.com/nba/76ers/news/sixers-joel-embiid-worked-with-okc-thunders-chet-holmgren",
            "googleUrl": "https://www.google.com/imgres?imgurl=https%3A%2F%2Fwww.si.com%2F.image%2Far_1%3A1%252Cc_fill%252Ccs_srgb%252Cfl_progressive%252Cq_auto%3Agood%252Cw_1200%2FMTkyODU5Mjg1OTcyMDY4MDQ4%2Fusatsi_19146062_168388689_lowres.jpg&tbnid=ZRYki1BU_JTsXM&imgrefurl=https%3A%2F%2Fwww.si.com%2Fnba%2F76ers%2Fnews%2Fsixers-joel-embiid-worked-with-okc-thunders-chet-holmgren&docid=Y-kDcn5vUJpPbM&w=1200&h=1200&ved=0ahUKEwiToJ3Wm_-CAxX6nokEHebSBh4QvFcIAygC",
            "position": 3
        },
        {
            "title": "76ers star Joel Embiid now U.S. citizen | NBA.com",
            "imageUrl": "https://cdn.nba.com/manage/2022/04/joel-embiid-reacts-iso-784x441.jpg",
            "imageWidth": 784,
            "imageHeight": 441,
            "thumbnailUrl": "https://encrypted-tbn0.gstatic.com/images?q=tbn:ANd9GcTP6Nyv3h6xSplOx2hJXyUyhFX3GqvhdwB3Rar_vZcrFLAQrVI&amp;s",
            "thumbnailWidth": 300,
            "thumbnailHeight": 168,
            "source": "NBA.com",
            "domain": "www.nba.com",
            "link": "https://www.nba.com/news/76ers-star-joel-embiid-now-us-citizen",
            "googleUrl": "https://www.google.com/imgres?imgurl=https%3A%2F%2Fcdn.nba.com%2Fmanage%2F2022%2F04%2Fjoel-embiid-reacts-iso-784x441.jpg&tbnid=pXhndovOA9dLFM&imgrefurl=https%3A%2F%2Fwww.nba.com%2Fnews%2F76ers-star-joel-embiid-now-us-citizen&docid=uuSf4-lYy-oGtM&w=784&h=441&ved=0ahUKEwiToJ3Wm_-CAxX6nokEHebSBh4QvFcIBCgD",
            "position": 4
        },
        {
            "title": "Philadelphia Passes Resolution to Name Joel Embiid City's MVP",
            "imageUrl": "https://people.com/thmb/KOkE3oygOMWE8rMF-dF0uBfrSe0=/1500x0/filters:no_upscale():max_bytes(150000):strip_icc():focal(625x19:627x21)/Joel-Embiid-e435ad7fb7cd451294191de9afa7ce7b.jpg",
            "imageWidth": 1306,
            "imageHeight": 2000,
            "thumbnailUrl": "https://encrypted-tbn0.gstatic.com/images?q=tbn:ANd9GcSGBMQj2Ftc2KoOMTP52We-14AfwefN9Tez1wXClah8XTlJhFI&amp;s",
            "thumbnailWidth": 181,
            "thumbnailHeight": 278,
            "source": "People",
            "domain": "people.com",
            "link": "https://people.com/sports/philadelphia-city-council-passes-resolution-to-name-joel-embiid-city-mvp/",
            "googleUrl": "https://www.google.com/imgres?imgurl=https%3A%2F%2Fpeople.com%2Fthmb%2FKOkE3oygOMWE8rMF-dF0uBfrSe0%3D%2F1500x0%2Ffilters%3Ano_upscale()%3Amax_bytes(150000)%3Astrip_icc()%3Afocal(625x19%3A627x21)%2FJoel-Embiid-e435ad7fb7cd451294191de9afa7ce7b.jpg&tbnid=m0D00RtkZ8ISNM&imgrefurl=https%3A%2F%2Fpeople.com%2Fsports%2Fphiladelphia-city-council-passes-resolution-to-name-joel-embiid-city-mvp%2F&docid=_JaARwbK28eg3M&w=1306&h=2000&ved=0ahUKEwiToJ3Wm_-CAxX6nokEHebSBh4QvFcIBSgE",
            "position": 5
        },
        {
            "title": "76ers celebrate Joel Embiid's scoring title, push Kia MVP ...",
            "imageUrl": "https://cdn.nba.com/manage/2022/04/joel-embiid-reaction.jpg",
            "imageWidth": 1920,
            "imageHeight": 1080,
            "thumbnailUrl": "https://encrypted-tbn0.gstatic.com/images?q=tbn:ANd9GcTcH-8GPrVb0evyA3u55UTCRW5onTZ79mbYDFkA8rXZ1Y1sVolt&amp;s",
            "thumbnailWidth": 300,
            "thumbnailHeight": 168,
            "source": "NBA.com",
            "domain": "www.nba.com",
            "link": "https://www.nba.com/news/76ers-celebrate-joel-embiids-scoring-title-push-kia-mvp-contention",
            "googleUrl": "https://www.google.com/imgres?imgurl=https%3A%2F%2Fcdn.nba.com%2Fmanage%2F2022%2F04%2Fjoel-embiid-reaction.jpg&tbnid=RTcR60KtdD5jTM&imgrefurl=https%3A%2F%2Fwww.nba.com%2Fnews%2F76ers-celebrate-joel-embiids-scoring-title-push-kia-mvp-contention&docid=cgfFjVjdwBEuRM&w=1920&h=1080&ved=0ahUKEwiToJ3Wm_-CAxX6nokEHebSBh4QvFcIBigF",
            "position": 6
        },
        {
            "title": "Philadelphia 76ers star Joel Embiid: the making of an NBA ...",
            "imageUrl": "https://i.guim.co.uk/img/media/533a4a5fddaf071603e00b31c8c1a290a8fd0185/0_36_2964_1778/master/2964.jpg?width=1200&height=1200&quality=85&auto=format&fit=crop&s=0726de770c91b4ae1c6431921336977d",
            "imageWidth": 1200,
            "imageHeight": 1200,
            "thumbnailUrl": "https://encrypted-tbn0.gstatic.com/images?q=tbn:ANd9GcTlbsJeiQZDfbAyEdNvYGwXHwPjUj4CPKRJEC7hALmlyfFdqns&amp;s",
            "thumbnailWidth": 225,
            "thumbnailHeight": 225,
            "source": "The Guardian",
            "domain": "www.theguardian.com",
            "link": "https://www.theguardian.com/sport/2021/oct/15/joel-embiid-philadelphia-sixers-nba-superhero",
            "googleUrl": "https://www.google.com/imgres?imgurl=https%3A%2F%2Fi.guim.co.uk%2Fimg%2Fmedia%2F533a4a5fddaf071603e00b31c8c1a290a8fd0185%2F0_36_2964_1778%2Fmaster%2F2964.jpg%3Fwidth%3D1200%26height%3D1200%26quality%3D85%26auto%3Dformat%26fit%3Dcrop%26s%3D0726de770c91b4ae1c6431921336977d&tbnid=K6jIoc1dxp_pyM&imgrefurl=https%3A%2F%2Fwww.theguardian.com%2Fsport%2F2021%2Foct%2F15%2Fjoel-embiid-philadelphia-sixers-nba-superhero&docid=xky1QvKFrjUuvM&w=1200&h=1200&ved=0ahUKEwiToJ3Wm_-CAxX6nokEHebSBh4QvFcIBygG",
            "position": 7
        },
        {
            "title": "Nobody Told Joel Embiid That Centers Don't Dominate The NBA ...",
            "imageUrl": "https://fivethirtyeight.com/wp-content/uploads/2021/06/AP21160101615182-4x3-1.jpg?w=575",
            "imageWidth": 575,
            "imageHeight": 431,
            "thumbnailUrl": "https://encrypted-tbn0.gstatic.com/images?q=tbn:ANd9GcRTDWYweEhH0qLyjsSg_A4DbAmiuDEftk-_BlbjKjIVWb9Y3J7_&amp;s",
            "thumbnailWidth": 259,
            "thumbnailHeight": 194,
            "source": "538 — Election Polls, Politics, and Analysis - ABC News",
            "domain": "fivethirtyeight.com",
            "link": "https://fivethirtyeight.com/features/nobody-told-joel-embiid-that-centers-dont-dominate-the-nba-anymore/",
            "googleUrl": "https://www.google.com/imgres?imgurl=https%3A%2F%2Ffivethirtyeight.com%2Fwp-content%2Fuploads%2F2021%2F06%2FAP21160101615182-4x3-1.jpg%3Fw%3D575&tbnid=zaJ-T_VoyKaPIM&imgrefurl=https%3A%2F%2Ffivethirtyeight.com%2Ffeatures%2Fnobody-told-joel-embiid-that-centers-dont-dominate-the-nba-anymore%2F&docid=tuqto1hOuvD49M&w=575&h=431&ved=0ahUKEwiToJ3Wm_-CAxX6nokEHebSBh4QvFcICCgH",
            "position": 8
        },
        {
            "title": "Hoops journey of Philadelphia 76ers phenom Joel Embiid a storybook ...",
            "imageUrl": "https://cdn.nba.com/manage/2020/10/USATSI_10307548-784x523.jpg",
            "imageWidth": 784,
            "imageHeight": 523,
            "thumbnailUrl": "https://encrypted-tbn0.gstatic.com/images?q=tbn:ANd9GcSmmGXldlY52moo-tVlI-B_FeGknBTLfRMg8L0FmIujaPXLB92C&amp;s",
            "thumbnailWidth": 275,
            "thumbnailHeight": 183,
            "source": "NBA.com",
            "domain": "www.nba.com",
            "link": "https://www.nba.com/news/joel-embiid-goes-volleyball-star-budding-presence-philadelphia-76ers",
            "googleUrl": "https://www.google.com/imgres?imgurl=https%3A%2F%2Fcdn.nba.com%2Fmanage%2F2020%2F10%2FUSATSI_10307548-784x523.jpg&tbnid=4SgwwobKjxHZMM&imgrefurl=https%3A%2F%2Fwww.nba.com%2Fnews%2Fjoel-embiid-goes-volleyball-star-budding-presence-philadelphia-76ers&docid=N0XWOfDV2CHIiM&w=784&h=523&ved=0ahUKEwiToJ3Wm_-CAxX6nokEHebSBh4QvFcICSgI",
            "position": 9
        },
        {
            "title": "Joel Embiid is struggling to find consistency - and so are the ...",
            "imageUrl": "https://e0.365dm.com/20/01/768x432/joel-embiid-philadelphia-76ers_4882205.jpg?20200103120220",
            "imageWidth": 768,
            "imageHeight": 432,
            "thumbnailUrl": "https://encrypted-tbn0.gstatic.com/images?q=tbn:ANd9GcTh1aIQ7sxIFMznFYywAekqSKvp6aabCRmH9Q3oAd57FBv9bo4_&amp;s",
            "thumbnailWidth": 300,
            "thumbnailHeight": 168,
            "source": "Sky Sports",
            "domain": "www.skysports.com",
            "link": "https://www.skysports.com/nba/news/36226/11900174/joel-embiid-is-struggling-to-find-consistency-and-so-are-the-philadelphia-76ers",
            "googleUrl": "https://www.google.com/imgres?imgurl=https%3A%2F%2Fe0.365dm.com%2F20%2F01%2F768x432%2Fjoel-embiid-philadelphia-76ers_4882205.jpg%3F20200103120220&tbnid=TlAiMEa1IiYJ8M&imgrefurl=https%3A%2F%2Fwww.skysports.com%2Fnba%2Fnews%2F36226%2F11900174%2Fjoel-embiid-is-struggling-to-find-consistency-and-so-are-the-philadelphia-76ers&docid=YEbl5_CZ_jGKCM&w=768&h=432&ved=0ahUKEwiToJ3Wm_-CAxX6nokEHebSBh4QvFcICigJ",
            "position": 10
        }
    ]
}